gitstack/__init__.py
gitstack/main.py
gitstack-0.2.0.dist-info/LICENSE.md
gitstack-0.2.0.dist-info/METADATA
gitstack-0.2.0.dist-info/WHEEL
gitstack-0.2.0.dist-info/entry_points.txt
gitstack-0.2.0.dist-info/top_level.txt
gitstack-0.2.0.dist-info/RECORD
