Metadata-Version: 2.1
Name: gitstack
Version: 0.2.0
Summary: An advanced modern version control system
License-File: LICENSE.md
Requires-Dist: click
Requires-Dist: tabulate
